{
	"configurations" : 
	[
		{
			"directories" : 
			[
				{
					"build" : ".",
					"jsonFile" : "directory-.-Debug-f5ebdc15457944623624.json",
					"minimumCMakeVersion" : 
					{
						"string" : "3.25"
					},
					"projectIndex" : 0,
					"source" : ".",
					"targetIndexes" : 
					[
						0,
						1,
						2,
						3,
						4,
						5
					]
				}
			],
			"name" : "Debug",
			"projects" : 
			[
				{
					"directoryIndexes" : 
					[
						0
					],
					"name" : "hiper",
					"targetIndexes" : 
					[
						0,
						1,
						2,
						3,
						4,
						5
					]
				}
			],
			"targets" : 
			[
				{
					"directoryIndex" : 0,
					"id" : "config_test::@6890427a1f51a3e7e1df",
					"jsonFile" : "target-config_test-Debug-36056715debb154d3347.json",
					"name" : "config_test",
					"projectIndex" : 0
				},
				{
					"directoryIndex" : 0,
					"id" : "hiper::@6890427a1f51a3e7e1df",
					"jsonFile" : "target-hiper-Debug-3f30b16b74aad09e7cf0.json",
					"name" : "hiper",
					"projectIndex" : 0
				},
				{
					"directoryIndex" : 0,
					"id" : "log_test::@6890427a1f51a3e7e1df",
					"jsonFile" : "target-log_test-Debug-3561588ad52aacbbef0b.json",
					"name" : "log_test",
					"projectIndex" : 0
				},
				{
					"directoryIndex" : 0,
					"id" : "mutex_test::@6890427a1f51a3e7e1df",
					"jsonFile" : "target-mutex_test-Debug-8d998f1801e1bb348f42.json",
					"name" : "mutex_test",
					"projectIndex" : 0
				},
				{
					"directoryIndex" : 0,
					"id" : "scheduler_test::@6890427a1f51a3e7e1df",
					"jsonFile" : "target-scheduler_test-Debug-cc0b28514c0537ea45c0.json",
					"name" : "scheduler_test",
					"projectIndex" : 0
				},
				{
					"directoryIndex" : 0,
					"id" : "try::@6890427a1f51a3e7e1df",
					"jsonFile" : "target-try-Debug-a1499f2a63a504d1d494.json",
					"name" : "try",
					"projectIndex" : 0
				}
			]
		}
	],
	"kind" : "codemodel",
	"paths" : 
	{
		"build" : "/home/leo/webserver/hiper/cmake-build-debug",
		"source" : "/home/leo/webserver/hiper"
	},
	"version" : 
	{
		"major" : 2,
		"minor" : 4
	}
}
